TermTk/__init__.py
TermTk/TTkAbstract/__init__.py
TermTk/TTkAbstract/abstractitemmodel.py
TermTk/TTkAbstract/abstractscrollarea.py
TermTk/TTkAbstract/abstractscrollview.py
TermTk/TTkCore/__init__.py
TermTk/TTkCore/canvas.py
TermTk/TTkCore/cfg.py
TermTk/TTkCore/color.py
TermTk/TTkCore/constant.py
TermTk/TTkCore/drag.py
TermTk/TTkCore/draw.py
TermTk/TTkCore/filebuffer.py
TermTk/TTkCore/helper.py
TermTk/TTkCore/log.py
TermTk/TTkCore/signal.py
TermTk/TTkCore/string.py
TermTk/TTkCore/timer.py
TermTk/TTkCore/ttk.py
TermTk/TTkCore/TTkTerm/__init__.py
TermTk/TTkCore/TTkTerm/colors.py
TermTk/TTkCore/TTkTerm/input.py
TermTk/TTkCore/TTkTerm/inputkey.py
TermTk/TTkCore/TTkTerm/inputmouse.py
TermTk/TTkCore/TTkTerm/readinputlinux.py
TermTk/TTkCore/TTkTerm/term.py
TermTk/TTkGui/__init__.py
TermTk/TTkGui/draw_ascii.py
TermTk/TTkGui/draw_utf8.py
TermTk/TTkGui/fileicon_ascii.py
TermTk/TTkGui/fileicon_nerd.py
TermTk/TTkGui/fileicon_utf8.py
TermTk/TTkGui/theme.py
TermTk/TTkLayouts/__init__.py
TermTk/TTkLayouts/boxlayout.py
TermTk/TTkLayouts/gridlayout.py
TermTk/TTkLayouts/layout.py
TermTk/TTkTemplates/__init__.py
TermTk/TTkTemplates/color.py
TermTk/TTkTemplates/data.py
TermTk/TTkTemplates/dragevents.py
TermTk/TTkTemplates/keyevents.py
TermTk/TTkTemplates/mouseevents.py
TermTk/TTkTemplates/text.py
TermTk/TTkTestWidgets/__init__.py
TermTk/TTkTestWidgets/logviewer.py
TermTk/TTkTestWidgets/testwidget.py
TermTk/TTkTestWidgets/testwidgetsizes.py
TermTk/TTkTypes/__init__.py
TermTk/TTkTypes/viewitem.py
TermTk/TTkWidgets/__init__.py
TermTk/TTkWidgets/about.py
TermTk/TTkWidgets/button.py
TermTk/TTkWidgets/checkbox.py
TermTk/TTkWidgets/combobox.py
TermTk/TTkWidgets/frame.py
TermTk/TTkWidgets/graph.py
TermTk/TTkWidgets/image.py
TermTk/TTkWidgets/label.py
TermTk/TTkWidgets/lineedit.py
TermTk/TTkWidgets/list_.py
TermTk/TTkWidgets/listwidget.py
TermTk/TTkWidgets/menubar.py
TermTk/TTkWidgets/radiobutton.py
TermTk/TTkWidgets/resizableframe.py
TermTk/TTkWidgets/scrollarea.py
pytest_fold-0.8.4.dist-info/LICENSE
pytest_fold-0.8.4.dist-info/METADATA
pytest_fold-0.8.4.dist-info/WHEEL
pytest_fold-0.8.4.dist-info/entry_points.txt
pytest_fold-0.8.4.dist-info/top_level.txt
pytest_fold-0.8.4.dist-info/RECORD
