Metadata-Version: 2.1
Name: pytest-fold
Version: 0.8.4
Summary: Capture Pytest output and when test run is complete, drop user into interactive text user interface
Home-page: https://github.com/jeffwright13/pytest-fold
Author: Jeff Wright
Author-email: jeff.washcloth@gmail.com
License: MIT
Keywords: pytest testing fold output logs fail pytermtk asciimatics textual single-source
Platform: UNKNOWN
Classifier: Framework :: Pytest
Classifier: Development Status :: 4 - Beta
Classifier: Intended Audience :: Developers
Classifier: Topic :: Software Development :: Testing
Classifier: Programming Language :: Python :: 3.8
Classifier: Programming Language :: Python :: 3.9
Classifier: Programming Language :: Python :: 3.10
Classifier: Operating System :: OS Independent
Classifier: License :: OSI Approved :: MIT License
Requires-Python: >=3.8
License-File: LICENSE
Requires-Dist: Faker (>=13.0.0)
Requires-Dist: pytest (>=6.2.5)
Requires-Dist: pyTermTk (>=0.9.0a43)
Requires-Dist: single-source (>=0.2.0)
Requires-Dist: strip-ansi (>=0.1.1)
Requires-Dist: textual (>=0.1.17)
